hw_latex/__init__.py
hw_latex/generate.py
hw_latex/latex.py
latex_table_image-0.0.6.dist-info/METADATA
latex_table_image-0.0.6.dist-info/WHEEL
latex_table_image-0.0.6.dist-info/top_level.txt
latex_table_image-0.0.6.dist-info/RECORD
